pyqtwaitingspinner/__about__.py
pyqtwaitingspinner/__init__.py
pyqtwaitingspinner/_creds.py
pyqtwaitingspinner/configurator.py
pyqtwaitingspinner/enum.py
pyqtwaitingspinner/func.py
pyqtwaitingspinner/msg.py
pyqtwaitingspinner/parameters.py
pyqtwaitingspinner/spinner.py
pyqtwaitingspinner/img/color-picker-default.16.png
pyqtwaitingspinner/img/color-picker-transparent.16.png
pyqtwaitingspinner/img/question.16.png
pyqtwaitingspinner-1.3.2.dist-info/METADATA
pyqtwaitingspinner-1.3.2.dist-info/WHEEL
pyqtwaitingspinner-1.3.2.dist-info/entry_points.txt
pyqtwaitingspinner-1.3.2.dist-info/licenses/LICENSE
pyqtwaitingspinner-1.3.2.dist-info/RECORD
