Metadata-Version: 2.3
Name: PyQtWaitingSpinner
Version: 1.3.2
Summary: (Py)QtWaitingSpinner is a highly configurable, custom Qt widget for showing "waiting" or "loading" spinner icons in (Py)Qt(6) applications.
Project-URL: Documentation, https://pyqtwaitingspinner.readthedocs.io/en/latest/
Project-URL: Issues, https://gitlab.com/Batticus/pyqtwaitingspinner/-/issues
Project-URL: Homepage, https://gitlab.com/Batticus/pyqtwaitingspinner
Author-email: Batticus <myshorts.mail@gmail.com>
License-Expression: MIT
License-File: LICENSE
Keywords: loading,pyqt,pyqt6,qt,qt6,spinner,waiting,widget
Classifier: Development Status :: 4 - Beta
Classifier: Environment :: X11 Applications :: Qt
Classifier: Framework :: Hatch
Classifier: Framework :: MkDocs
Classifier: Framework :: Pytest
Classifier: Intended Audience :: Developers
Classifier: License :: OSI Approved :: MIT License
Classifier: Natural Language :: English
Classifier: Operating System :: Microsoft :: Windows :: Windows 10
Classifier: Operating System :: OS Independent
Classifier: Operating System :: POSIX :: Linux
Classifier: Programming Language :: Python
Classifier: Programming Language :: Python :: 3 :: Only
Classifier: Programming Language :: Python :: 3.8
Classifier: Programming Language :: Python :: 3.9
Classifier: Programming Language :: Python :: 3.10
Classifier: Programming Language :: Python :: 3.11
Classifier: Programming Language :: Python :: 3.12
Classifier: Programming Language :: Python :: Implementation :: CPython
Classifier: Topic :: Software Development :: Libraries
Classifier: Topic :: Software Development :: Libraries :: Python Modules
Classifier: Topic :: Software Development :: Widget Sets
Requires-Python: >=3.8
Requires-Dist: pyqt6==6.7.1
Requires-Dist: pyyaml==6.0.1
